idealgeo/__init__.py
idealgeo/__main__.py
idealgeo/cli.py
idealgeo/client.py
idealgeo/geometries/__init__.py
idealgeo/geometries/buffer.py
idealgeo/geometries/custom.py
idealgeo/geometries/location.py
idealgeo/geometries/region.py
idealgeo/insights/__init__.py
idealgeo/vehicletraffic/__init__.py
idealgeo-0.1.0.dist-info/AUTHORS.rst
idealgeo-0.1.0.dist-info/LICENSE
idealgeo-0.1.0.dist-info/METADATA
idealgeo-0.1.0.dist-info/WHEEL
idealgeo-0.1.0.dist-info/entry_points.txt
idealgeo-0.1.0.dist-info/top_level.txt
idealgeo-0.1.0.dist-info/RECORD
